AUTHORS.rst
CONTRIBUTING.rst
HISTORY.rst
LICENSE
MANIFEST.in
README.rst
requirements.txt
requirements_test.txt
setup.py
static.py
staticserve.egg-info/PKG-INFO
staticserve.egg-info/SOURCES.txt
staticserve.egg-info/dependency_links.txt
staticserve.egg-info/not-zip-safe
staticserve.egg-info/requires.txt
staticserve.egg-info/top_level.txt