Metadata-Version: 1.1
Name: staticserve
Version: 0.1.4
Summary: A simple WSGI way to serve static (or mixed) content.
Home-page: https://github.com/pydanny/staticserve
Author: Daniel Greenfeld
Author-email: pydanny@gmail.com
License: LGPL
Keywords: wsgi web http static content webapps
Platform: UNKNOWN
Classifier: Development Status :: 3 - Alpha
Classifier: Environment :: Web Environment
Classifier: Intended Audience :: Developers
Classifier: License :: OSI Approved :: GNU Library or Lesser General Public License (LGPL)
Classifier: Natural Language :: English
Classifier: Operating System :: OS Independent
Classifier: Programming Language :: Python :: 2.6
Classifier: Programming Language :: Python :: 2.7
Classifier: Programming Language :: Python :: 3.3
Classifier: Topic :: Software Development :: Libraries
Classifier: Topic :: Utilities
